{
  "name": "listCampaigns",
  "runtime": "babel",
  "description": "Serverless Lambda function for project: MoonMail-v2",
  "customName": "${project}-campaigns-listCampaigns",
  "customRole": false,
  "handler": "campaigns/listCampaigns/handler.default",
  "timeout": 6,
  "memorySize": 1024,
  "authorizer": {},
  "custom": {
    "excludePatterns": []
  },
  "endpoints": [
    {
      "path": "/campaigns",
      "method": "GET",
      "type": "AWS",
      "authorizationType": "none",
      "authorizerFunction": false,
      "apiKeyRequired": false,
      "requestParameters": {},
      "requestTemplates": {
        "application/json": {
          "user_id": "$input.params('user_id')"
        }
      },
      "responses": "$${responses}"
    }
  ],
  "events": [],
  "environment": {
    "SERVERLESS_PROJECT": "${project}",
    "SERVERLESS_STAGE": "${stage}",
    "SERVERLESS_REGION": "${region}",
    "CAMPAIGNS_TABLE": "$${campaignsTable}",
    "DEBUG": "true"
  },
  "vpc": {
    "securityGroupIds": [],
    "subnetIds": []
  }
}
